axi_counter.v
module axi_counter (
    input  wire        aclk,
    input  wire        aresetn,
    // Read Address Channel
    input  wire [31:0] araddr,
    input  wire        arvalid,
    output reg         arready,
    // Read Data Channel
    output reg  [31:0] rdata,
    output reg         rvalid,
    input  wire        rready
);
    // Internal 4-bit counter logic
    reg [3:0] count_reg;
    always @(posedge aclk or negedge aresetn) begin
        if (!aresetn) count_reg <= 4'b0;
        else          count_reg <= count_reg + 1'b1;
    end

    // AXI-Lite Read Logic (Simplified Handshake)
    always @(posedge aclk or negedge aresetn) begin
        if (!aresetn) begin
            arready <= 1'b0;
            rvalid  <= 1'b0;
            rdata   <= 32'b0;
        end else begin
            // 1. Accept Address
            arready <= 1'b1; 
            
            // 2. When Address is Valid, Send Data
            if (arvalid && arready) begin
                rdata  <= {28'b0, count_reg}; // Put counter value in data bus
                rvalid <= 1'b1;
            end 
            
            // 3. Complete Handshake
            if (rvalid && rready) begin
                rvalid <= 1'b0;
            end
        end
    end

    initial begin
        $dumpfile("dump.vcd");
        $dumpvars(0, axi_counter);
    end
endmodule

dump.vcd
$date
	Tue Mar 10 10:13:43 2026
$end
$version
	Icarus Verilog
$end
$timescale
	1ps
$end
$scope module axi_counter $end
$var wire 1 ! aclk $end
$var wire 32 " araddr [31:0] $end
$var wire 1 # aresetn $end
$var wire 1 $ arvalid $end
$var wire 1 % rready $end
$var reg 1 & arready $end
$var reg 4 ' count_reg [3:0] $end
$var reg 32 ( rdata [31:0] $end
$var reg 1 ) rvalid $end
$upscope $end
$enddefinitions $end
$comment Show the parameter values. $end
$dumpall
$end
#0
$dumpvars
0)
b0 (
b0 '
0&
z%
z$
0#
bz "
1!
$end
#5000
0!
#10000
1!
#15000
0!
#20000
1%
1$
b0 "
b1 '
1&
1!
1#
#25000
0!
#30000
1)
b1 (
b10 '
1!
#35000
0!
#40000
b11 '
0)
b10 (
1!
#45000
0!
#50000
1)
b11 (
b100 '
1!
#55000
0!
#60000
b101 '
0)
b100 (
1!
#65000
0!
#70000
1)
b101 (
b110 '
1!
#75000
0!
#80000
b111 '
0)
b110 (
1!
#85000
0!
#90000
1)
b111 (
b1000 '
1!
#95000
0!
#100000
b1001 '
0)
b1000 (
1!
#105000
0!
#110000
1)
b1001 (
b1010 '
1!
#115000
0!
#120000
b1011 '
0)
b1010 (
1!
#125000
0!
#130000
1)
b1011 (
b1100 '
1!
#135000
0!
#140000
b1101 '
0)
b1100 (
1!
#145000
0!
#150000
1)
b1101 (
b1110 '
1!
#155000
0!
#160000
b1111 '
0)
b1110 (
1!
#165000
0!
#170000
1)
b1111 (
b0 '
1!
#175000
0!
#180000
b1 '
0)
b0 (
1!
#185000
0!
#190000
1)
b1 (
b10 '
1!
#195000
0!
#200000
b11 '
0)
b10 (
1!
#205000
0!
#210000
1)
b11 (
b100 '
1!
#215000
0!
#220000
b101 '
0)
b100 (
1!
#225000
0!
#230000
1)
b101 (
b110 '
1!
#235000
0!
#240000
b111 '
0)
b110 (
1!
#245000
0!
#250000
1)
b111 (
b1000 '
1!
#255000
0!
#260000
b1001 '
0)
b1000 (
1!
#265000
0!
#270000
1)
b1001 (
b1010 '
1!
#275000
0!
#280000
b1011 '
0)
b1010 (
1!
#285000
0!
#290000
1)
b1011 (
b1100 '
1!
#295000
0!
#300000
b1101 '
0)
b1100 (
1!
#305000
0!
#310000
1)
b1101 (
b1110 '
1!
#315000
0!
#320000
b1111 '
0)
b1110 (
1!
#325000
0!
#330000
1)
b1111 (
b0 '
1!
#335000
0!
#340000
b1 '
0)
b0 (
1!
#345000
0!
#350000
1)
b1 (
b10 '
1!
#355000
0!
#360000
b11 '
0)
b10 (
1!
#365000
0!
#370000
1)
b11 (
b100 '
1!
#375000
0!
#380000
b101 '
0)
b100 (
1!
#385000
0!
#390000
1)
b101 (
b110 '
1!
#395000
0!
#400000
b111 '
0)
b110 (
1!
#405000
0!
#410000
1)
b111 (
b1000 '
1!
#415000
0!
#420000
b1001 '
0)
b1000 (
1!
#425000
0!
#430000
1)
b1001 (
b1010 '
1!
#435000
0!
#440000
b1011 '
0)
b1010 (
1!
#445000
0!
#450000
1)
b1011 (
b1100 '
1!
#455000
0!
#460000
b1101 '
0)
b1100 (
1!
#465000
0!
#470000
1)
b1101 (
b1110 '
1!
#475000
0!
#480000
b1111 '
0)
b1110 (
1!
#485000
0!
#490000
1)
b1111 (
b0 '
1!
#495000
0!
#500000
b1 '
0)
b0 (
1!
#505000
0!
#510000
1)
b1 (
b10 '
1!
#515000
0!
#520000
b11 '
0)
b10 (
1!
#525000
0!
#530000
1)
b11 (
b100 '
1!
#535000
0!
#540000
b101 '
0)
b100 (
1!
#545000
0!
#550000
1)
b101 (
b110 '
1!
#555000
0!
#560000
b111 '
0)
b110 (
1!
#565000
0!
#570000
1)
b111 (
b1000 '
1!
#575000
0!
#580000
b1001 '
0)
b1000 (
1!
#585000
0!
#590000
1)
b1001 (
b1010 '
1!
#595000
0!
#600000
b1011 '
0)
b1010 (
1!
#605000
0!
#610000
1)
b1011 (
b1100 '
1!
#615000
0!
#620000
b1101 '
0)
b1100 (
1!
#625000
0!
#630000
1)
b1101 (
b1110 '
1!
#635000
0!
#640000
b1111 '
0)
b1110 (
1!
#645000
0!
#650000
1)
b1111 (
b0 '
1!
#655000
0!
#660000
b1 '
0)
b0 (
1!
#665000
0!
#670000
1)
b1 (
b10 '
1!
#675000
0!
#680000
b11 '
0)
b10 (
1!
#685000
0!
#690000
1)
b11 (
b100 '
1!
#695000
0!
#700000
b101 '
0)
b100 (
1!
#705000
0!
#710000
1)
b101 (
b110 '
1!
#715000
0!
#720000
b111 '
0)
b110 (
1!
#725000
0!
#730000
1)
b111 (
b1000 '
1!
#735000
0!
#740000
b1001 '
0)
b1000 (
1!
#745000
0!
#750000
1)
b1001 (
b1010 '
1!
#755000
0!
#760000
b1011 '
0)
b1010 (
1!
#765000
0!
#770000
1)
b1011 (
b1100 '
1!
#775000
0!
#780000
b1101 '
0)
b1100 (
1!
#785000
0!
#790000
1)
b1101 (
b1110 '
1!
#795000
0!
#800000
b1111 '
0)
b1110 (
1!
#805000
0!
#810000
1)
b1111 (
b0 '
1!
#815000
0!
#820000
b1 '
0)
b0 (
1!
#825000
0!
#830000
1)
b1 (
b10 '
1!
#835000
0!
#840000
b11 '
0)
b10 (
1!
#845000
0!
#850000
1)
b11 (
b100 '
1!
#855000
0!
#860000
b101 '
0)
b100 (
1!
#865000
0!
#870000
1)
b101 (
b110 '
1!
#875000
0!
#880000
b111 '
0)
b110 (
1!
#885000
0!
#890000
1)
b111 (
b1000 '
1!
#895000
0!
#900000
b1001 '
0)
b1000 (
1!
#905000
0!
#910000
1)
b1001 (
b1010 '
1!
#915000
0!
#920000
b1011 '
0)
b1010 (
1!
#925000
0!
#930000
1)
b1011 (
b1100 '
1!
#935000
0!
#940000
b1101 '
0)
b1100 (
1!
#945000
0!
#950000
1)
b1101 (
b1110 '
1!
#955000
0!
#960000
b1111 '
0)
b1110 (
1!
#965000
0!
#970000
1)
b1111 (
b0 '
1!
#975000
0!
#980000
b1 '
0)
b0 (
1!
#985000
0!
#990000
1)
b1 (
b10 '
1!
#995000
0!
#1000000
b11 '
0)
b10 (
1!
#1005000
0!
#1010000
1)
b11 (
b100 '
1!
#1015000
0!
#1020000
b101 '
0)
b100 (
1!
#1025000
0!
#1030000
1)
b101 (
b110 '
1!
#1035000
0!
#1040000
b111 '
0)
b110 (
1!
#1045000
0!
#1050000
1)
b111 (
b1000 '
1!
#1055000
0!
#1060000
b1001 '
0)
b1000 (
1!
#1065000
0!
#1070000
1)
b1001 (
b1010 '
1!
#1075000
0!
#1080000
b1011 '
0)
b1010 (
1!
#1085000
0!
#1090000
1)
b1011 (
b1100 '
1!
#1095000
0!
#1100000
b1101 '
0)
b1100 (
1!
#1105000
0!
#1110000
1)
b1101 (
b1110 '
1!
#1115000
0!
#1120000
b1111 '
0)
b1110 (
1!
#1125000
0!
#1130000
1)
b1111 (
b0 '
1!
#1135000
0!
#1140000
b1 '
0)
b0 (
1!
#1145000
0!
#1150000
1)
b1 (
b10 '
1!
#1155000
0!
#1160000
b11 '
0)
b10 (
1!
#1165000
0!
#1170000
1)
b11 (
b100 '
1!
#1175000
0!
#1180000
b101 '
0)
b100 (
1!
#1185000
0!
#1190000
1)
b101 (
b110 '
1!
#1195000
0!
#1200000
b111 '
0)
b110 (
1!
#1205000
0!
#1210000
1)
b111 (
b1000 '
1!
#1215000
0!
#1220000
b1001 '
0)
b1000 (
1!
#1225000
0!
#1230000
1)
b1001 (
b1010 '
1!
#1235000
0!
#1240000
b1011 '
0)
b1010 (
1!
#1245000
0!
#1250000
1)
b1011 (
b1100 '
1!
#1255000
0!
#1260000
b1101 '
0)
b1100 (
1!
#1265000
0!
#1270000
1)
b1101 (
b1110 '
1!
#1275000
0!
#1280000
b1111 '
0)
b1110 (
1!
#1285000
0!
#1290000
1)
b1111 (
b0 '
1!
#1295000
0!
#1300000
b1 '
0)
b0 (
1!
#1305000
0!
#1310000
1)
b1 (
b10 '
1!
#1315000
0!
#1320000
b11 '
0)
b10 (
1!
#1325000
0!
#1330000
1)
b11 (
b100 '
1!
#1335000
0!
#1340000
b101 '
0)
b100 (
1!
#1345000
0!
#1350000
1)
b101 (
b110 '
1!
#1355000
0!
#1360000
b111 '
0)
b110 (
1!
#1365000
0!
#1370000
1)
b111 (
b1000 '
1!
#1375000
0!
#1380000
b1001 '
0)
b1000 (
1!
#1385000
0!
#1390000
1)
b1001 (
b1010 '
1!
#1395000
0!
#1400000
b1011 '
0)
b1010 (
1!
#1405000
0!
#1410000
1)
b1011 (
b1100 '
1!
#1415000
0!
#1420000
b1101 '
0)
b1100 (
1!
#1425000
0!
#1430000
1)
b1101 (
b1110 '
1!
#1435000
0!
#1440000
b1111 '
0)
b1110 (
1!
#1445000
0!
#1450000
1)
b1111 (
b0 '
1!
#1455000
0!
#1460000
b1 '
0)
b0 (
1!
#1465000
0!
#1470000
1)
b1 (
b10 '
1!
#1475000
0!
#1480000
b11 '
0)
b10 (
1!
#1485000
0!
#1490000
1)
b11 (
b100 '
1!
#1495000
0!
#1500000
b101 '
0)
b100 (
1!
#1505000
0!
#1510000
1)
b101 (
b110 '
1!
#1515000
0!
#1520000
b111 '
0)
b110 (
1!
#1525000
0!
#1530000
1)
b111 (
b1000 '
1!
#1535000
0!
#1540000
b1001 '
0)
b1000 (
1!
#1545000
0!
#1550000
1)
b1001 (
b1010 '
1!
#1555000
0!
#1560000
b1011 '
0)
b1010 (
1!
#1565000
0!
#1570000
1)
b1011 (
b1100 '
1!
#1575000
0!
#1580000
b1101 '
0)
b1100 (
1!
#1585000
0!
#1590000
1)
b1101 (
b1110 '
1!
#1595000
0!
#1600000
b1111 '
0)
b1110 (
1!
#1605000
0!
#1610000
1)
b1111 (
b0 '
1!
#1615000
0!
#1620000
b1 '
0)
b0 (
1!
#1625000
0!
#1630000
1)
b1 (
b10 '
1!
#1635000
0!
#1640000
b11 '
0)
b10 (
1!
#1645000
0!
#1650000
1)
b11 (
b100 '
1!
#1655000
0!
#1660000
b101 '
0)
b100 (
1!
#1665000
0!
#1670000
1)
b101 (
b110 '
1!
#1675000
0!
#1680000
b111 '
0)
b110 (
1!
#1685000
0!
#1690000
1)
b111 (
b1000 '
1!
#1695000
0!
#1700000
b1001 '
0)
b1000 (
1!
#1705000
0!
#1710000
1)
b1001 (
b1010 '
1!
#1715000
0!
#1720000
b1011 '
0)
b1010 (
1!
#1725000
0!
#1730000
1)
b1011 (
b1100 '
1!
#1735000
0!
#1740000
b1101 '
0)
b1100 (
1!
#1745000
0!
#1750000
1)
b1101 (
b1110 '
1!
#1755000
0!
#1760000
b1111 '
0)
b1110 (
1!
#1765000
0!
#1770000
1)
b1111 (
b0 '
1!
#1775000
0!
#1780000
b1 '
0)
b0 (
1!
#1785000
0!
#1790000
1)
b1 (
b10 '
1!
#1795000
0!
#1800000
b11 '
0)
b10 (
1!
#1805000
0!
#1810000
1)
b11 (
b100 '
1!
#1815000
0!
#1820000
b101 '
0)
b100 (
1!
#1825000
0!
#1830000
1)
b101 (
b110 '
1!
#1835000
0!
#1840000
b111 '
0)
b110 (
1!
#1845000
0!
#1850000
1)
b111 (
b1000 '
1!
#1855000
0!
#1860000
b1001 '
0)
b1000 (
1!
#1865000
0!
#1870000
1)
b1001 (
b1010 '
1!
#1875000
0!
#1880000
b1011 '
0)
b1010 (
1!
#1885000
0!
#1890000
1)
b1011 (
b1100 '
1!
#1895000
0!
#1900000
b1101 '
0)
b1100 (
1!
#1905000
0!
#1910000
1)
b1101 (
b1110 '
1!
#1915000
0!
#1920000
b1111 '
0)
b1110 (
1!
#1925000
0!
#1930000
1)
b1111 (
b0 '
1!
#1935000
0!
#1940000
b1 '
0)
b0 (
1!
#1945000
0!
#1950000
1)
b1 (
b10 '
1!
#1955000
0!
#1960000
b11 '
0)
b10 (
1!
#1965000
0!
#1970000
1)
b11 (
b100 '
1!
#1975000
0!
#1980000
b101 '
0)
b100 (
1!
#1985000
0!
#1990000
1)
b101 (
b110 '
1!
#1995000
0!
#2000000
b111 '
0)
b110 (
1!
#2005000
0!
#2010000
1)
b111 (
b1000 '
1!
#2015000
0!
#2020000
b1001 '
0)
b1000 (
1!
#2025000
0!
#2030000
1)
b1001 (
b1010 '
1!
#2035000
0!
#2040000
b1011 '
0)
b1010 (
1!
#2045000
0!
#2050000
1)
b1011 (
b1100 '
1!
#2055000
0!
#2060000
b1101 '
0)
b1100 (
1!
#2065000
0!
#2070000
1)
b1101 (
b1110 '
1!
#2075000
0!
#2080000
b1111 '
0)
b1110 (
1!
#2085000
0!
#2090000
1)
b1111 (
b0 '
1!
#2095000
0!
#2100000
b1 '
0)
b0 (
1!
#2105000
0!
#2110000
1)
b1 (
b10 '
1!
#2115000
0!
#2120000
b11 '
0)
b10 (
1!
#2125000
0!
#2130000
1)
b11 (
b100 '
1!
#2135000
0!
#2140000
b101 '
0)
b100 (
1!
#2145000
0!
#2150000
1)
b101 (
b110 '
1!
#2155000
0!
#2160000
b111 '
0)
b110 (
1!
#2165000
0!
#2170000
1)
b111 (
b1000 '
1!
#2175000
0!
#2180000
b1001 '
0)
b1000 (
1!
#2185000
0!
#2190000
1)
b1001 (
b1010 '
1!
#2195000
0!
#2200000
b1011 '
0)
b1010 (
1!
#2205000
0!
#2210000
1)
b1011 (
b1100 '
1!
#2215000
0!
#2220000
b1101 '
0)
b1100 (
1!
#2225000
0!
#2230000
1)
b1101 (
b1110 '
1!
#2235000
0!
#2240000
b1111 '
0)
b1110 (
1!
#2245000
0!
#2250000
1)
b1111 (
b0 '
1!
#2255000
0!
#2260000
b1 '
0)
b0 (
1!
#2265000
0!
#2270000
1)
b1 (
b10 '
1!
#2275000
0!
#2280000
b11 '
0)
b10 (
1!
#2285000
0!
#2290000
1)
b11 (
b100 '
1!
#2295000
0!
#2300000
b101 '
0)
b100 (
1!
#2305000
0!
#2310000
1)
b101 (
b110 '
1!
#2315000
0!
#2320000
b111 '
0)
b110 (
1!
#2325000
0!
#2330000
1)
b111 (
b1000 '
1!
#2335000
0!
#2340000
b1001 '
0)
b1000 (
1!
#2345000
0!
#2350000
1)
b1001 (
b1010 '
1!
#2355000
0!
#2360000
b1011 '
0)
b1010 (
1!
#2365000
0!
#2370000
1)
b1011 (
b1100 '
1!
#2375000
0!
#2380000
b1101 '
0)
b1100 (
1!
#2385000
0!
#2390000
1)
b1101 (
b1110 '
1!
#2395000
0!
#2400000
b1111 '
0)
b1110 (
1!
#2405000
0!
#2410000
1)
b1111 (
b0 '
1!
#2415000
0!
#2420000
b1 '
0)
b0 (
1!
#2425000
0!
#2430000
1)
b1 (
b10 '
1!
#2435000
0!
#2440000
b11 '
0)
b10 (
1!
#2445000
0!
#2450000
1)
b11 (
b100 '
1!
#2455000
0!
#2460000
b101 '
0)
b100 (
1!
#2465000
0!
#2470000
1)
b101 (
b110 '
1!
#2475000
0!
#2480000
b111 '
0)
b110 (
1!
#2485000
0!
#2490000
1)
b111 (
b1000 '
1!
#2495000
0!
#2500000
b1001 '
0)
b1000 (
1!
#2505000
0!
#2510000
1)
b1001 (
b1010 '
1!
#2515000
0!
#2520000
b1011 '
0)
b1010 (
1!
#2525000
0!
#2530000
1)
b1011 (
b1100 '
1!
#2535000
0!
#2540000
b1101 '
0)
b1100 (
1!
#2545000
0!
#2550000
1)
b1101 (
b1110 '
1!
#2555000
0!
#2560000
b1111 '
0)
b1110 (
1!
#2565000
0!
#2570000
1)
b1111 (
b0 '
1!
#2575000
0!
#2580000
b1 '
0)
b0 (
1!
#2585000
0!
#2590000
1)
b1 (
b10 '
1!
#2595000
0!
#2600000
b11 '
0)
b10 (
1!
#2605000
0!
#2610000
1)
b11 (
b100 '
1!
#2615000
0!
#2620000
b101 '
0)
b100 (
1!
#2625000
0!
#2630000
1)
b101 (
b110 '
1!
#2635000
0!
#2640000
b111 '
0)
b110 (
1!
#2645000
0!
#2650000
1)
b111 (
b1000 '
1!
#2655000
0!
#2660000
b1001 '
0)
b1000 (
1!
#2665000
0!
#2670000
1)
b1001 (
b1010 '
1!
#2675000
0!
#2680000
b1011 '
0)
b1010 (
1!
#2685000
0!
#2690000
1)
b1011 (
b1100 '
1!
#2695000
0!
#2700000
b1101 '
0)
b1100 (
1!
#2705000
0!
#2710000
1)
b1101 (
b1110 '
1!
#2715000
0!
#2720000
b1111 '
0)
b1110 (
1!
#2725000
0!
#2730000
1)
b1111 (
b0 '
1!
#2735000
0!
#2740000
b1 '
0)
b0 (
1!
#2745000
0!
#2750000
1)
b1 (
b10 '
1!
#2755000
0!
#2760000
b11 '
0)
b10 (
1!
#2765000
0!
#2770000
1)
b11 (
b100 '
1!
#2775000
0!
#2780000
b101 '
0)
b100 (
1!
#2785000
0!
#2790000
1)
b101 (
b110 '
1!
#2795000
0!
#2800000
b111 '
0)
b110 (
1!
#2805000
0!
#2810000
1)
b111 (
b1000 '
1!
#2815000
0!
#2820000
b1001 '
0)
b1000 (
1!
#2825000
0!
#2830000
1)
b1001 (
b1010 '
1!
#2835000
0!
#2840000
b1011 '
0)
b1010 (
1!
#2845000
0!
#2850000
1)
b1011 (
b1100 '
1!
#2855000
0!
#2860000
b1101 '
0)
b1100 (
1!
#2865000
0!
#2870000
1)
b1101 (
b1110 '
1!
#2875000
0!
#2880000
b1111 '
0)
b1110 (
1!
#2885000
0!
#2890000
1)
b1111 (
b0 '
1!
#2895000
0!
#2900000
b1 '
0)
b0 (
1!
#2905000
0!
#2910000
1)
b1 (
b10 '
1!
#2915000
0!
#2920000
b11 '
0)
b10 (
1!
#2925000
0!
#2930000
1)
b11 (
b100 '
1!
#2935000
0!
#2940000
b101 '
0)
b100 (
1!
#2945000
0!
#2950000
1)
b101 (
b110 '
1!
#2955000
0!
#2960000
b111 '
0)
b110 (
1!
#2965000
0!
#2970000
1)
b111 (
b1000 '
1!
#2975000
0!
#2980000
b1001 '
0)
b1000 (
1!
#2985000
0!
#2990000
1)
b1001 (
b1010 '
1!
#2995000
0!
#3000000
b1011 '
0)
b1010 (
1!
#3005000
0!
#3010000
1)
b1011 (
b1100 '
1!
#3015000
0!
#3020000
b1101 '
0)
b1100 (
1!
#3025000
0!
#3030000
1)
b1101 (
b1110 '
1!
#3035000
0!
#3040000
b1111 '
0)
b1110 (
1!
#3045000
0!
#3050000
1)
b1111 (
b0 '
1!
#3055000
0!
#3060000
b1 '
0)
b0 (
1!
#3065000
0!
#3070000
1)
b1 (
b10 '
1!
#3075000
0!
#3080000
b11 '
0)
b10 (
1!
#3085000
0!
#3090000
1)
b11 (
b100 '
1!
#3095000
0!
#3100000
b101 '
0)
b100 (
1!
#3105000
0!
#3110000
1)
b101 (
b110 '
1!
#3115000
0!
#3120000
b111 '
0)
b110 (
1!
#3125000
0!
#3130000
1)
b111 (
b1000 '
1!
#3135000
0!
#3140000
b1001 '
0)
b1000 (
1!
#3145000
0!
#3150000
1)
b1001 (
b1010 '
1!
#3155000
0!
#3160000
b1011 '
0)
b1010 (
1!
#3165000
0!
#3170000
1)
b1011 (
b1100 '
1!
#3175000
0!
#3180000
b1101 '
0)
b1100 (
1!
#3185000
0!
#3190000
1)
b1101 (
b1110 '
1!
#3195000
0!
#3200000
b1111 '
0)
b1110 (
1!
#3205000
0!
#3210000
1)
b1111 (
b0 '
1!
#3215000
0!
#3220000
b1 '
0)
b0 (
1!
#3225000
0!
#3230000
1)
b1 (
b10 '
1!
#3235000
0!
#3240000
b11 '
0)
b10 (
1!
#3245000
0!
#3250000
1)
b11 (
b100 '
1!
#3255000
0!
#3260000
b101 '
0)
b100 (
1!
#3265000
0!
#3270000
1)
b101 (
b110 '
1!
#3275000
0!
#3280000
b111 '
0)
b110 (
1!
#3285000
0!
#3290000
1)
b111 (
b1000 '
1!
#3295000
0!
#3300000
b1001 '
0)
b1000 (
1!
#3305000
0!
#3310000
1)
b1001 (
b1010 '
1!
#3315000
0!
#3320000
b1011 '
0)
b1010 (
1!
#3325000
0!
#3330000
1)
b1011 (
b1100 '
1!
#3335000
0!
#3340000
b1101 '
0)
b1100 (
1!
#3345000
0!
#3350000
1)
b1101 (
b1110 '
1!
#3355000
0!
#3360000
b1111 '
0)
b1110 (
1!
#3365000
0!
#3370000
1)
b1111 (
b0 '
1!
#3375000
0!
#3380000
b1 '
0)
b0 (
1!
#3385000
0!
#3390000
1)
b1 (
b10 '
1!
#3395000
0!
#3400000
b11 '
0)
b10 (
1!
#3405000
0!
#3410000
1)
b11 (
b100 '
1!
#3415000
0!
#3420000
b101 '
0)
b100 (
1!
#3425000
0!
#3430000
1)
b101 (
b110 '
1!
#3435000
0!
#3440000
b111 '
0)
b110 (
1!
#3445000
0!
#3450000
1)
b111 (
b1000 '
1!
#3455000
0!
#3460000
b1001 '
0)
b1000 (
1!
#3465000
0!
#3470000
1)
b1001 (
b1010 '
1!
#3475000
0!
#3480000
b1011 '
0)
b1010 (
1!
#3485000
0!
#3490000
1)
b1011 (
b1100 '
1!
#3495000
0!
#3500000
b1101 '
0)
b1100 (
1!
#3505000
0!
#3510000
1)
b1101 (
b1110 '
1!
#3515000
0!
#3520000
b1111 '
0)
b1110 (
1!
#3525000
0!
#3530000
1)
b1111 (
b0 '
1!
#3535000
0!
#3540000
b1 '
0)
b0 (
1!
#3545000
0!
#3550000
1)
b1 (
b10 '
1!
#3555000
0!
#3560000
b11 '
0)
b10 (
1!
#3565000
0!
#3570000
1)
b11 (
b100 '
1!
#3575000
0!
#3580000
b101 '
0)
b100 (
1!
#3585000
0!
#3590000
1)
b101 (
b110 '
1!
#3595000
0!
#3600000
b111 '
0)
b110 (
1!
#3605000
0!
#3610000
1)
b111 (
b1000 '
1!
#3615000
0!
#3620000
b1001 '
0)
b1000 (
1!
#3625000
0!
#3630000
1)
b1001 (
b1010 '
1!
#3635000
0!
#3640000
b1011 '
0)
b1010 (
1!
#3645000
0!
#3650000
1)
b1011 (
b1100 '
1!
#3655000
0!
#3660000
b1101 '
0)
b1100 (
1!
#3665000
0!
#3670000
1)
b1101 (
b1110 '
1!
#3675000
0!
#3680000
b1111 '
0)
b1110 (
1!
#3685000
0!
#3690000
1)
b1111 (
b0 '
1!
#3695000
0!
#3700000
b1 '
0)
b0 (
1!
#3705000
0!
#3710000
1)
b1 (
b10 '
1!
#3715000
0!
#3720000
b11 '
0)
b10 (
1!
#3725000
0!
#3730000
1)
b11 (
b100 '
1!
#3735000
0!
#3740000
b101 '
0)
b100 (
1!
#3745000
0!
#3750000
1)
b101 (
b110 '
1!
#3755000
0!
#3760000
b111 '
0)
b110 (
1!
#3765000
0!
#3770000
1)
b111 (
b1000 '
1!
#3775000
0!
#3780000
b1001 '
0)
b1000 (
1!
#3785000
0!
#3790000
1)
b1001 (
b1010 '
1!
#3795000
0!
#3800000
b1011 '
0)
b1010 (
1!
#3805000
0!
#3810000
1)
b1011 (
b1100 '
1!
#3815000
0!
#3820000
b1101 '
0)
b1100 (
1!
#3825000
0!
#3830000
1)
b1101 (
b1110 '
1!
#3835000
0!
#3840000
b1111 '
0)
b1110 (
1!
#3845000
0!
#3850000
1)
b1111 (
b0 '
1!
#3855000
0!
#3860000
b1 '
0)
b0 (
1!
#3865000
0!
#3870000
1)
b1 (
b10 '
1!
#3875000
0!
#3880000
b11 '
0)
b10 (
1!
#3885000
0!
#3890000
1)
b11 (
b100 '
1!
#3895000
0!
#3900000
b101 '
0)
b100 (
1!
#3905000
0!
#3910000
1)
b101 (
b110 '
1!
#3915000
0!
#3920000
b111 '
0)
b110 (
1!
#3925000
0!
#3930000
1)
b111 (
b1000 '
1!
#3935000
0!
#3940000
b1001 '
0)
b1000 (
1!
#3945000
0!
#3950000
1)
b1001 (
b1010 '
1!
#3955000
0!
#3960000
b1011 '
0)
b1010 (
1!
#3965000
0!
#3970000
1)
b1011 (
b1100 '
1!
#3975000
0!
#3980000
b1101 '
0)
b1100 (
1!
#3985000
0!
#3990000
1)
b1101 (
b1110 '
1!
#3995000
0!
#4000000
b1111 '
0)
b1110 (
1!
#4005000
0!
#4010000
1)
b1111 (
b0 '
1!
#4015000
0!
#4020000
b1 '
0)
b0 (
1!
#4025000
0!
#4030000
1)
b1 (
b10 '
1!
#4035000
0!
#4040000
b11 '
0)
b10 (
1!
#4045000
0!
#4050000
1)
b11 (
b100 '
1!
#4055000
0!
#4060000
b101 '
0)
b100 (
1!
#4065000
0!
#4070000
1)
b101 (
b110 '
1!
#4075000
0!
#4080000
b111 '
0)
b110 (
1!
#4085000
0!
#4090000
1)
b111 (
b1000 '
1!
#4095000
0!
#4100000
b1001 '
0)
b1000 (
1!
#4105000
0!
#4110000
1)
b1001 (
b1010 '
1!
#4115000
0!
#4120000
b1011 '
0)
b1010 (
1!
#4125000
0!
#4130000
1)
b1011 (
b1100 '
1!
#4135000
0!
#4140000
b1101 '
0)
b1100 (
1!
#4145000
0!
#4150000
1)
b1101 (
b1110 '
1!
#4155000
0!
#4160000
b1111 '
0)
b1110 (
1!
#4165000
0!
#4170000
1)
b1111 (
b0 '
1!
#4175000
0!
#4180000
b1 '
0)
b0 (
1!
#4185000
0!
#4190000
1)
b1 (
b10 '
1!
#4195000
0!
#4200000
b11 '
0)
b10 (
1!
#4205000
0!
#4210000
1)
b11 (
b100 '
1!
#4215000
0!
#4220000
b101 '
0)
b100 (
1!
#4225000
0!
#4230000
1)
b101 (
b110 '
1!
#4235000
0!
#4240000
b111 '
0)
b110 (
1!
#4245000
0!
#4250000
1)
b111 (
b1000 '
1!
#4255000
0!
#4260000
b1001 '
0)
b1000 (
1!
#4265000
0!
#4270000
1)
b1001 (
b1010 '
1!
#4275000
0!
#4280000
b1011 '
0)
b1010 (
1!
#4285000
0!
#4290000
1)
b1011 (
b1100 '
1!
#4295000
0!
#4300000
b1101 '
0)
b1100 (
1!
#4305000
0!
#4310000
1)
b1101 (
b1110 '
1!
#4315000
0!
#4320000
b1111 '
0)
b1110 (
1!
#4325000
0!
#4330000
1)
b1111 (
b0 '
1!
#4335000
0!
#4340000
b1 '
0)
b0 (
1!
#4345000
0!
#4350000
1)
b1 (
b10 '
1!
#4355000
0!
#4360000
b11 '
0)
b10 (
1!
#4365000
0!
#4370000
1)
b11 (
b100 '
1!
#4375000
0!
#4380000
b101 '
0)
b100 (
1!
#4385000
0!
#4390000
1)
b101 (
b110 '
1!
#4395000
0!
#4400000
b111 '
0)
b110 (
1!
#4405000
0!
#4410000
1)
b111 (
b1000 '
1!
#4415000
0!
#4420000
b1001 '
0)
b1000 (
1!
#4425000
0!
#4430000
1)
b1001 (
b1010 '
1!
#4435000
0!
#4440000
b1011 '
0)
b1010 (
1!
#4445000
0!
#4450000
1)
b1011 (
b1100 '
1!
#4455000
0!
#4460000
b1101 '
0)
b1100 (
1!
#4465000
0!
#4470000
1)
b1101 (
b1110 '
1!
#4475000
0!
#4480000
b1111 '
0)
b1110 (
1!
#4485000
0!
#4490000
1)
b1111 (
b0 '
1!
#4495000
0!
#4500000
b1 '
0)
b0 (
1!
#4505000
0!
#4510000
1)
b1 (
b10 '
1!
#4515000
0!
#4520000
b11 '
0)
b10 (
1!
#4525000
0!
#4530000
1)
b11 (
b100 '
1!
#4535000
0!
#4540000
b101 '
0)
b100 (
1!
#4545000
0!
#4550000
1)
b101 (
b110 '
1!
#4555000
0!
#4560000
b111 '
0)
b110 (
1!
#4565000
0!
#4570000
1)
b111 (
b1000 '
1!
#4575000
0!
#4580000
b1001 '
0)
b1000 (
1!
#4585000
0!
#4590000
1)
b1001 (
b1010 '
1!
#4595000
0!
#4600000
b1011 '
0)
b1010 (
1!
#4605000
0!
#4610000
1)
b1011 (
b1100 '
1!
#4615000
0!
#4620000
b1101 '
0)
b1100 (
1!
#4625000
0!
#4630000
1)
b1101 (
b1110 '
1!
#4635000
0!
#4640000
b1111 '
0)
b1110 (
1!
#4645000
0!
#4650000
1)
b1111 (
b0 '
1!
#4655000
0!
#4660000
b1 '
0)
b0 (
1!
#4665000
0!
#4670000
1)
b1 (
b10 '
1!
#4675000
0!
#4680000
b11 '
0)
b10 (
1!
#4685000
0!
#4690000
1)
b11 (
b100 '
1!
#4695000
0!
#4700000
b101 '
0)
b100 (
1!
#4705000
0!
#4710000
1)
b101 (
b110 '
1!
#4715000
0!
#4720000
b111 '
0)
b110 (
1!
#4725000
0!
#4730000
1)
b111 (
b1000 '
1!
#4735000
0!
#4740000
b1001 '
0)
b1000 (
1!
#4745000
0!
#4750000
1)
b1001 (
b1010 '
1!
#4755000
0!
#4760000
b1011 '
0)
b1010 (
1!
#4765000
0!
#4770000
1)
b1011 (
b1100 '
1!
#4775000
0!
#4780000
b1101 '
0)
b1100 (
1!
#4785000
0!
