axi_handshake.v
module axi_counter (
    input  wire        aclk,
    input  wire        aresetn,
    // Write Address Channel
    input  wire [31:0] awaddr,
    input  wire        awvalid,
    output reg         awready,
    // Write Data Channel
    input  wire [31:0] wdata,
    input  wire        wvalid,
    output reg         wready,
    // Read Address Channel
    input  wire [31:0] araddr,
    input  wire        arvalid,
    output reg         arready,
    // Read Data Channel
    output reg  [31:0] rdata,
    output reg         rvalid,
    input  wire        rready
);
    // 4-bit internal counter
    reg [3:0] count_reg;

    // Combined AXI-Lite Logic
    always @(posedge aclk or negedge aresetn) begin
        if (!aresetn) begin
            count_reg <= 4'b0;
            awready <= 1'b0;
            wready  <= 1'b0;
            arready <= 1'b0;
            rvalid  <= 1'b0;
            rdata   <= 32'b0;
        end else begin
            // --- WRITE LOGIC (Slave is always ready) ---
            awready <= 1'b1;
            wready  <= 1'b1;

            if (awvalid && awready && wvalid && wready) begin
                count_reg <= wdata[3:0]; // Load counter from Bus
            end else begin
                count_reg <= count_reg + 1'b1; // Default: Increment
            end

            // --- READ LOGIC ---
            arready <= 1'b1;
            if (arvalid && arready) begin
                rdata  <= {28'b0, count_reg};
                rvalid <= 1'b1;
            end 
            
            // Clear RVALID once Master acknowledges (RREADY)
            if (rvalid && rready) begin
                rvalid <= 1'b0;
            end
        end
    end

    // Standard for simulation viewing
    initial begin
        $dumpfile("dump.vcd");
        $dumpvars(0, axi_counter);
    end
endmodule

dump.vcd
$date
	Tue Mar 10 11:02:46 2026
$end
$version
	Icarus Verilog
$end
$timescale
	1ps
$end
$scope module axi_counter $end
$var wire 1 ! aclk $end
$var wire 32 " araddr [31:0] $end
$var wire 1 # aresetn $end
$var wire 1 $ arvalid $end
$var wire 32 % awaddr [31:0] $end
$var wire 1 & awvalid $end
$var wire 1 ' rready $end
$var wire 32 ( wdata [31:0] $end
$var wire 1 ) wvalid $end
$var reg 1 * arready $end
$var reg 1 + awready $end
$var reg 4 , count_reg [3:0] $end
$var reg 32 - rdata [31:0] $end
$var reg 1 . rvalid $end
$var reg 1 / wready $end
$upscope $end
$enddefinitions $end
$comment Show the parameter values. $end
$dumpall
$end
#0
$dumpvars
0/
0.
b0 -
b0 ,
0+
0*
z)
bz (
z'
z&
bz %
z$
0#
bz "
1!
$end
#5000
0!
#10000
1!
#15000
0!
#20000
1)
b1010 (
1&
b0 %
1*
b1 ,
1/
1+
1!
1#
#25000
0!
#30000
b1010 ,
1!
#31000
0)
0&
#35000
0!
#40000
b1011 ,
1!
#45000
0!
#50000
1'
1$
b0 "
b1100 ,
1!
#55000
0!
#60000
1.
b1100 -
b1101 ,
1!
#65000
0!
#70000
0.
b1101 -
b1110 ,
1!
